pycaddy/__init__.py
pycaddy/convert.py
pycaddy/aggregator/__init__.py
pycaddy/aggregator/aggregator.py
pycaddy/aggregator/flattenable.py
pycaddy/dict_utils/__init__.py
pycaddy/dict_utils/flatten.py
pycaddy/dict_utils/hashing.py
pycaddy/dict_utils/merge.py
pycaddy/dict_utils/split.py
pycaddy/dict_utils/unflatten.py
pycaddy/dict_utils/utils.py
pycaddy/ledger/__init__.py
pycaddy/ledger/ledger.py
pycaddy/ledger/naming_strategy.py
pycaddy/ledger/run_record.py
pycaddy/ledger/singleton.py
pycaddy/ledger/status.py
pycaddy/load/__init__.py
pycaddy/load/load_json.py
pycaddy/project/__init__.py
pycaddy/project/project.py
pycaddy/project/session.py
pycaddy/project/structs.py
pycaddy/project/utils.py
pycaddy/save/__init__.py
pycaddy/save/save_figure.py
pycaddy/save/save_json.py
pycaddy/scheduler/__init__.py
pycaddy/scheduler/scheduler.py
pycaddy/sweeper/__init__.py
pycaddy/sweeper/base.py
pycaddy/sweeper/chain_sweep.py
pycaddy/sweeper/construct.py
pycaddy/sweeper/dict_sweep.py
pycaddy/sweeper/empty.py
pycaddy/sweeper/normalize.py
pycaddy/sweeper/strategies.py
pycaddy/utils/__init__.py
pycaddy/utils/path_like.py
pycaddy-0.2.0.dist-info/METADATA
pycaddy-0.2.0.dist-info/WHEEL
pycaddy-0.2.0.dist-info/licenses/LICENSE
pycaddy-0.2.0.dist-info/RECORD
