Metadata-Version: 2.4
Name: pycaddy
Version: 0.2.0
Summary: A Python toolbox caddy for experiment tracking, parameter sweeping, and automation tasks
Project-URL: Homepage, https://github.com/HutoriHunzu/pycaddy
Project-URL: Repository, https://github.com/HutoriHunzu/pycaddy
Author-email: Uri Goldblatt <uri.goldblatt@gmail.com>
License-Expression: MIT
License-File: LICENSE
Keywords: automation,experiment-tracking,parameter-sweep,toolbox
Classifier: Development Status :: 3 - Alpha
Classifier: Intended Audience :: Developers
Classifier: Intended Audience :: Science/Research
Classifier: Programming Language :: Python :: 3
Classifier: Programming Language :: Python :: 3.11
Classifier: Programming Language :: Python :: 3.12
Classifier: Topic :: Scientific/Engineering
Classifier: Topic :: Software Development :: Libraries :: Python Modules
Requires-Python: >=3.11
Requires-Dist: filelock>=3.18.0
Requires-Dist: matplotlib
Requires-Dist: pint
Requires-Dist: pydantic>=2.6.4
Provides-Extra: dev
Requires-Dist: pytest; extra == 'dev'
Requires-Dist: ruff; extra == 'dev'
